__init__.py
accord.py
discord_objects.py
accord.py-0.0.2.dist-info/LICENSE
accord.py-0.0.2.dist-info/METADATA
accord.py-0.0.2.dist-info/WHEEL
accord.py-0.0.2.dist-info/top_level.txt
accord.py-0.0.2.dist-info/RECORD
