Metadata-Version: 2.1
Name: accord.py
Version: 0.0.2
Summary: Testing library for the discord.py library
Author-email: Eetu Asikainen <eetu.asikainen1204@gmail.com>
Project-URL: Homepage, https://github.com/EddieTheCubeHead/accord.py
Project-URL: Bug Tracker, https://github.com/EddieTheCubeHead/accord.py/issues
Keywords: testing,discord,discord.py
Classifier: Development Status :: 3 - Alpha
Classifier: Intended Audience :: Developers
Classifier: License :: OSI Approved :: MIT License
Classifier: Operating System :: OS Independent
Requires-Python: >=3.11
License-File: LICENSE
